dtsdance/__init__.py
dtsdance/bytecloud.py
dtsdance/ddutil.py
dtsdance/dflow.py
dtsdance/dsyncer.py
dtsdance/feishu_base.py
dtsdance/feishu_table.py
dtsdance/metrics_fe.py
dtsdance/s3.py
dtsdance/spacex.py
dtsdance/tcc_inner.py
dtsdance/tcc_open.py
dts_dance-0.2.6.dist-info/METADATA
dts_dance-0.2.6.dist-info/WHEEL
dts_dance-0.2.6.dist-info/RECORD
