Metadata-Version: 2.4
Name: dts-dance
Version: 0.2.6
Summary: dts dance lib
Keywords: observation,tools
Requires-Python: >=3.12
Requires-Dist: boto3>=1.42.35
Requires-Dist: loguru<0.8.0,>=0.7.3
Requires-Dist: pyyaml<7.0.0,>=6.0.3
Requires-Dist: requests-toolbelt==1.0.0
Requires-Dist: requests<3.0.0,>=2.32.5
